AUTHORS.txt
LICENSE.txt
MANIFEST.in
README.rst
setup.cfg
setup.py
django_brightcove/__init__.py
django_brightcove/fields.py
django_brightcove/models.py
django_brightcove/urls.py
django_brightcove/utils.py
django_brightcove/views.py
django_brightcove/widgets.py
django_brightcove.egg-info/PKG-INFO
django_brightcove.egg-info/SOURCES.txt
django_brightcove.egg-info/dependency_links.txt
django_brightcove.egg-info/pbr.json
django_brightcove.egg-info/requires.txt
django_brightcove.egg-info/top_level.txt
django_brightcove/migrations/0001_initial.py
django_brightcove/migrations/__init__.py
django_brightcove/south_migrations/0001_initial.py
django_brightcove/south_migrations/__init__.py
django_brightcove/static/brightcove/css/brightcove.css
django_brightcove/static/brightcove/js/brightcove.js
django_brightcove/templates/select_widget.html
django_brightcove/templates/tags/brightcove_player.html
django_brightcove/templatetags/__init__.py
django_brightcove/templatetags/brightcove.py