Metadata-Version: 1.1
Name: django-brightcove
Version: 0.0.6
Summary: Manages integration of brightcove into django.
Home-page: http://www.revsquare.com
Author: Guillaume Pousseo
Author-email: guillaumepousseo@revsquare.com
License: BSD License
Platform: OS Independent
Classifier: Development Status :: 5 - Production/Stable
Classifier: Environment :: Web Environment
Classifier: Framework :: Django
Classifier: Intended Audience :: Developers
Classifier: License :: OSI Approved :: BSD License
Classifier: Operating System :: OS Independent
Classifier: Programming Language :: Python
Classifier: Programming Language :: Python :: 2
Classifier: Programming Language :: Python :: 2.6
Classifier: Programming Language :: Python :: 2.7
Classifier: Topic :: Software Development :: Libraries :: Python Modules
Classifier: Topic :: Documentation
